smasunnyisland/__init__.py
smasunnyisland/sma_controller.py
SMASunnyIsland-1.42.dist-info/LICENSE
SMASunnyIsland-1.42.dist-info/METADATA
SMASunnyIsland-1.42.dist-info/WHEEL
SMASunnyIsland-1.42.dist-info/top_level.txt
SMASunnyIsland-1.42.dist-info/RECORD
