Metadata-Version: 2.1
Name: SMASunnyIsland
Version: 1.42
Summary: A Python library for controlling SMA Sunny Island inverters
Home-page: https://github.com/HarmvandenBrink/SMA_Sunny_Island_Controller
Author: Harm van den Brink
Author-email: Harm van den Brink <harmvandenbrink@gmail.com>
Project-URL: Homepage, https://github.com/HarmvandenBrink/SMA_Sunny_Island_Controller
Project-URL: Issues, https://github.com/HarmvandenBrink/SMA_Sunny_Island_Controller/issues
Classifier: Programming Language :: Python :: 3
Classifier: License :: OSI Approved :: MIT License
Classifier: Operating System :: OS Independent
Requires-Python: >=3.9
License-File: LICENSE
Requires-Dist: pyserial
Requires-Dist: pymodbus ==2.5.3
Requires-Dist: pysunspec ==2.1.1
